torchtitan/__init__.py
torchtitan/train.py
torchtitan/components/checkpoint.py
torchtitan/components/dataloader.py
torchtitan/components/loss.py
torchtitan/components/lr_scheduler.py
torchtitan/components/metrics.py
torchtitan/components/optimizer.py
torchtitan/components/tokenizer.py
torchtitan/components/validate.py
torchtitan/components/ft/__init__.py
torchtitan/components/ft/manager.py
torchtitan/components/ft/config/__init__.py
torchtitan/components/ft/config/job_config.py
torchtitan/components/ft/diloco/__init__.py
torchtitan/components/ft/diloco/protocol.py
torchtitan/components/ft/diloco/utils.py
torchtitan/components/quantization/__init__.py
torchtitan/components/quantization/float8.py
torchtitan/components/quantization/mx.py
torchtitan/components/quantization/utils.py
torchtitan/config/__init__.py
torchtitan/config/job_config.py
torchtitan/config/manager.py
torchtitan/distributed/__init__.py
torchtitan/distributed/activation_checkpoint.py
torchtitan/distributed/dual_pipe_v.py
torchtitan/distributed/expert_parallel.py
torchtitan/distributed/parallel_dims.py
torchtitan/distributed/pipeline_parallel.py
torchtitan/distributed/tensor_parallel.py
torchtitan/distributed/utils.py
torchtitan/distributed/deepep/__init__.py
torchtitan/distributed/deepep/deepep.py
torchtitan/experiments/__init__.py
torchtitan/experiments/autoparallel/job_config.py
torchtitan/experiments/autoparallel/deepseek_v3/__init__.py
torchtitan/experiments/autoparallel/deepseek_v3/parallelize_deepseekv3.py
torchtitan/experiments/autoparallel/llama3/__init__.py
torchtitan/experiments/autoparallel/llama3/parallelize_llama.py
torchtitan/experiments/autoparallel/local_map_deepseek_v3/__init__.py
torchtitan/experiments/autoparallel/local_map_deepseek_v3/args.py
torchtitan/experiments/autoparallel/local_map_deepseek_v3/model.py
torchtitan/experiments/autoparallel/local_map_deepseek_v3/parallelize_deepseekv3.py
torchtitan/experiments/autoparallel/tests/__init__.py
torchtitan-0.2.1.dist-info/licenses/LICENSE
torchtitan-0.2.1.dist-info/METADATA
torchtitan-0.2.1.dist-info/WHEEL
torchtitan-0.2.1.dist-info/top_level.txt
torchtitan-0.2.1.dist-info/RECORD
