Metadata-Version: 2.4
Name: torchtitan
Version: 0.2.1
Summary: A PyTorch native platform for training generative AI models
Author-email: PyTorch Team <packages@pytorch.org>
License: BSD 3-Clause License
Project-URL: GitHub, https://github.com/pytorch/torchtitan
Project-URL: Documentation, https://github.com/pytorch/torchtitan/tree/main/docs
Project-URL: Issues, https://github.com/pytorch/torchtitan/issues
Keywords: pytorch,training,llm
Requires-Python: >=3.10
License-File: LICENSE
Requires-Dist: torchdata>=0.8.0
Requires-Dist: datasets>=2.21.0
Requires-Dist: tokenizers
Requires-Dist: tomli>=1.1.0
Requires-Dist: fsspec
Requires-Dist: tyro
Requires-Dist: tensorboard
Requires-Dist: einops
Requires-Dist: pillow
Provides-Extra: dev
Requires-Dist: pre-commit; extra == "dev"
Requires-Dist: pytest; extra == "dev"
Requires-Dist: pytest-cov; extra == "dev"
Requires-Dist: wandb; extra == "dev"
Requires-Dist: tomli_w; extra == "dev"
Requires-Dist: expecttest; extra == "dev"
Dynamic: license-file
